rtl/lock_in/common.sv
// common.sv
`ifndef COMMON_SV
`define COMMON_SV

// Global Macros
`define DATA_WIDTH 32
`define INSTRUCTION_WIDTH 32
`define DATA_MEMORY_ADDRESS_WIDTH 32
`define INSTRUCTION_MEMORY_ADDRESS_WIDTH 32

// Type Definitions
typedef logic [`DATA_WIDTH-1:0] data_t;
typedef logic [`INSTRUCTION_WIDTH-1:0] instruction_t;
typedef logic [`DATA_MEMORY_ADDRESS_WIDTH-1:0] data_memory_address_t;
typedef logic [`INSTRUCTION_MEMORY_ADDRESS_WIDTH-1:0] instruction_memory_address_t;

typedef struct packed {
    instruction_memory_address_t base_instructions_address;
    data_memory_address_t base_data_address; // This is where kernel function arguments are stored
    data_t num_blocks;
    data_t num_warps_per_block;
} kernel_config_t;

// RISC-V Definitions
`define OPCODE_WIDTH 7
`define FUNCT3_WIDTH 3
`define FUNCT4_WIDTH 4

// Halt Instruction Opcode
`define OPCODE_HALT     3'b110

// Vector-Scalar Instruction Opcodes (SX_SLTI and SX_SLT)
// SX_SLTI sets one bit of a scalar register based on thread's comparison result
`define OPCODE_SX_SLT   7'b1111110        // SX_SLT rd, rs1, rs2 <=> rd[id] = rs1 < rs2 ? 1 : 0
`define OPCODE_SX_SLTI  7'b1111101        // SX_SLTI rd, rs1, imm <=> rd[id] = rs1 < imm ? 1 : 0

// Instruction Opcodes
// The entire opcode is 7 bits, the most significant bit decides whether the instruction is vector or scalar
`define OPCODE_R        3'b000          // Used by all R-type instructions (ADD, SUB, SLL, SLT, XOR, SRL, SRA)
`define OPCODE_I        3'b001          // Used by ALU I-type instructions (ADDI, SLTI, XORI, ORI, ANDI, SLLI, SRLI, SRAI)
`define OPCODE_UP       3'b011          // Used by LUI
`define OPCODE_M        3'b100          // Used by load instructions (LB, LH, LW)
`define OPCODE_F        3'b010          // Floating Point F-Type
`define OPCODE_J        3'b111

// Those instructions can only be used by scalar instructions
`define OPCODE_C        3'b111          // Control Flow C-Type

typedef logic [`OPCODE_WIDTH-1:0] opcode_t;
typedef logic [`FUNCT3_WIDTH-1:0] funct3_t;
typedef logic [`FUNCT4_WIDTH-1:0] funct4_t;
typedef logic [11:0] imm12_t;

// alu instructions enum
typedef enum logic [3:0] {
    // register instructions
    ADD,
    SUB,
    MUL,
    DIV,
    SLT,
    SGT,
    SEQ,
    SNEZ,
    MIN,
    ABS,

    ADDI,
    MULI,
    DIVI,
    SLLI,

    // compare instructions
    BEQ,

    // jump instructions
    JAL
} alu_instruction_t;

typedef enum logic [3:0] {
    FADD,
    FSUB,
    FMUL,
    FDIV,
    FLT,
    FNEG,
    FEQ,
    FMIN,
    FABS,
    FCVT_W_S,
    FCVT_S_W
} alu_f_instruction_t;

// warp state enum
typedef enum logic [2:0] {
    WARP_IDLE,
    WARP_FETCH,
    WARP_DECODE,
    WARP_REQUEST,
    WARP_WAIT,
    WARP_EXECUTE,
    WARP_UPDATE,
    WARP_DONE
} warp_state_t;

// fetcher state enum
typedef enum logic [1:0] {
    FETCHER_IDLE,
    FETCHER_FETCHING,
    FETCHER_DONE
} fetcher_state_t;

// lsu state enum
typedef enum logic [1:0] {
    LSU_IDLE,
    LSU_REQUESTING,
    LSU_WAITING,
    LSU_DONE
} lsu_state_t;

// reg input mux
typedef enum logic [2:0] {
    ALU_OUT,
    LSU_OUT,
    IMMEDIATE,
    PC_PLUS_1,
    VECTOR_TO_SCALAR
} reg_input_mux_t;

function automatic data_t sign_extend_14(logic [13:0] imm14);
    data_t signed_imm14;
    if (imm14[13]) begin
        signed_imm14 = {{18{1'b1}}, imm14};
    end else begin
        signed_imm14 = {{18{1'b0}}, imm14};
    end
    return signed_imm14;
endfunction

function automatic data_t sign_extend_15(logic[14:0] imm15);
    data_t signed_imm15;
    if (imm15[14]) begin
        signed_imm15 = {{17{1'b1}}, imm15};
    end else begin
        signed_imm15 = {{17{1'b0}}, imm15};
    end
    return signed_imm15;
endfunction

function automatic data_t sign_extend_18(logic[17:0] imm18);
    data_t signed_imm18;
    if (imm18[17]) begin
        signed_imm18 = {{14{1'b1}}, imm18};
    end else begin
        signed_imm18 = {{14{1'b0}}, imm18};
    end
    return signed_imm18;
endfunction

// sign extend function for 21-bit immediate values
function automatic data_t sign_extend_28(logic[27:0] imm28);
    data_t signed_imm28;
    if (imm28[27]) begin
        signed_imm28 = {{4{1'b1}}, imm28};
    end else begin
        signed_imm28 = {{4{1'b0}}, imm28};
    end
    return signed_imm28;
endfunction

`endif // COMMON_SV

rtl/lock_in/decoder.sv
`default_nettype none
`timescale 1ns/1ns

`include "common.sv"

module decoder(
    input   wire                clk,
    input   wire                reset,
    input   warp_state_t        warp_state,

    input   instruction_t       instruction,

    output  reg                 decoded_reg_write_enable,
    output  reg                 decoded_mem_write_enable,
    output  reg                 decoded_mem_read_enable,
    output  reg                 decoded_branch,
    output  reg_input_mux_t     decoded_reg_input_mux,
    output  reg                 decoded_scalar_instruction,
    output  data_t              decoded_immediate,
    output  reg [4:0]           decoded_rd_address,
    output  reg [4:0]           decoded_rs1_address,
    output  reg [4:0]           decoded_rs2_address,
    output  alu_instruction_t   decoded_alu_instruction,

    output  reg                 decoded_halt
);
    // Extract fields from instruction
    wire         scalar     = instruction[6];
    wire [5:0]   inst       = instruction[5:0];
    wire [2:0]   opcode     = instruction[31:29];
    wire [4:0]   rd         = instruction[4:0];
    wire [2:0]   funct3     = instruction[14:12];
    wire [4:0]   rs1        = instruction[9:5];
    wire [3:0]   funct4     = instruction[13:10];
    wire [4:0]   rs2        = instruction[18:14];

    wire [13:0]  imm_i      = instruction[27:14];
    wire [14:0]  imm_load   = instruction[28:14];
    wire [14:0]  imm_s      = {instruction[28:19], instruction[4:0]};
    wire [17:0]  imm_b      = {instruction[28:19], instruction[13], instruction[4:0], 2'b00};
    wire [31:12] imm_u      = instruction[28:9];
    wire [27:0]  imm_j      = {instruction[28:13], instruction[9:0], 2'b00};

    always @(posedge clk) begin
        if (reset) begin
            // Set outputs to default values
            decoded_reg_write_enable <= 0;
            decoded_mem_write_enable <= 0;
            decoded_mem_read_enable <= 0;
            decoded_branch <= 0;
            decoded_reg_input_mux <= ALU_OUT;
            decoded_immediate <= {`DATA_WIDTH{1'b0}};
            decoded_rd_address <= 5'b0;
            decoded_rs1_address <= 5'b0;
            decoded_rs2_address <= 5'b0;
            decoded_alu_instruction <= ADDI;
            decoded_halt <= 0;
            decoded_scalar_instruction <= 0;
        end else if (warp_state == WARP_DECODE) begin
            // Default assignments for new decode
            decoded_reg_write_enable <= 0;
            decoded_reg_input_mux <= ALU_OUT;
            decoded_immediate <= {`DATA_WIDTH{1'b0}};
            decoded_rd_address <= 5'b0;
            decoded_rs1_address <= 5'b0;
            decoded_rs2_address <= 5'b0;
            decoded_alu_instruction <= ADDI;
            decoded_mem_read_enable <= 0;
            decoded_mem_write_enable <= 0;
            decoded_branch <= 0;
            decoded_halt <= 0;
            decoded_scalar_instruction <= 0;

            if (opcode == `OPCODE_HALT) begin
                decoded_halt <= 1;
            // end else if (opcode == `OPCODE_SX_SLT) begin
            //     decoded_scalar_instruction  <= 0; // This is a vector-scalar instruction
            //     decoded_rd_address          <= rd;
            //     decoded_rs1_address         <= rs1;
            //     decoded_rs2_address         <= rs2;
            //     decoded_reg_write_enable    <= 1;
            //     decoded_reg_input_mux       <= VECTOR_TO_SCALAR;
            //     decoded_alu_instruction     <= SLT;
            // end else if (opcode == `OPCODE_SX_SLTI) begin
            //     decoded_scalar_instruction  <= 0; // This is a vector-scalar instruction
            //     decoded_rd_address          <= rd;
            //     decoded_rs1_address         <= rs1;
            //     decoded_immediate           <= sign_extend_14(imm_i);
            //     decoded_reg_write_enable    <= 1;
            //     decoded_reg_input_mux       <= VECTOR_TO_SCALAR;
            //     decoded_alu_instruction     <= SLTI;                // not implemented yet
            end else if (opcode == `OPCODE_J) begin
                unique case (funct3) 
                    3'b000: begin
                        
                        decoded_alu_instruction     <= JAL;
                        $display("Decoding instruction 0b%32b", instruction);
                        decoded_immediate           <= sign_extend_28(imm_j);
                        
                    end

                    3'b001: begin
                        
                        // Branch instructions (e.g., BEQ, BNE)
                        decoded_rs1_address         <= rs1;
                        decoded_rs2_address         <= rs2;
                        decoded_immediate           <= sign_extend_18(imm_b);
                        decoded_branch              <= 1;
                        decoded_alu_instruction     <= BEQZ;

                    end

                    default: $error("Invalid R-type instruction with funct3 %b", funct3);
                endcase                
            end else begin
                case (opcode)
                    `OPCODE_R: begin
                        // Vector R-type instructions
                        decoded_rd_address          <= rd;
                        decoded_rs1_address         <= rs1;
                        decoded_rs2_address         <= rs2;
                        decoded_reg_write_enable    <= 1;
                        decoded_reg_input_mux       <= ALU_OUT;

                        // Determine the ALU instruction
                        unique case (funct4)
                            4'b0000: decoded_alu_instruction <= ADD;
                            4'b0001: decoded_alu_instruction <= SUB;
                            4'b0010: decoded_alu_instruction <= MUL;
                            4'b0011: decoded_alu_instruction <= DIV;
                            4'b0100: decoded_alu_instruction <= SLT;
                            4'b0110: decoded_alu_instruction <= SEQ;
                            4'b0111: decoded_alu_instruction <= SNEZ;
                            4'b1000: decoded_alu_instruction <= MIN;
                            4'b1001: decoded_alu_instruction <= ABS;
                            4'b1010: decoded_alu_instruction <= SLL;
                            default: $error("Invalid R-type instruction with funct4 %b", funct4);
                        endcase
                    end
                    `OPCODE_I: begin
                        // Vector I-type instructions
                        decoded_rd_address <= rd;
                        decoded_rs1_address <= rs1;
                        decoded_reg_write_enable <= 1;
                        decoded_reg_input_mux <= ALU_OUT;
                        decoded_immediate <= sign_extend_14(imm_i);

                        unique case (funct4)
                            4'b0000: decoded_alu_instruction <= ADDI;
                            4'b0010: decoded_alu_instruction <= MULI;
                            4'b0011: decoded_alu_instruction <= DIVI;
                            4'b1010: decoded_alu_instruction <= SLLI;
                            default: $error("Invalid I-type instruction with funct4 %b", funct4);
                        endcase
                    end

                    `OPCODE_F: begin
                        // Vector I-type instructions
                        decoded_rd_address          <= rd;
                        decoded_rs1_address         <= rs1;
                        decoded_reg_write_enable    <= 1;
                        decoded_reg_input_mux       <= ALU_OUT;

                        unique case (funct4)
                            4'b0000: decoded_alu_instruction <= FADD;
                            4'b0001: decoded_alu_instruction <= FSUB;
                            4'b0010: decoded_alu_instruction <= FMUL;
                            4'b0011: decoded_alu_instruction <= FDIV;
                            4'b0100: decoded_alu_instruction <= FLT;
                            4'b0101: decoded_alu_instruction <= FNEG;
                            4'b0110: decoded_alu_instruction <= FEQ;
                            4'b0111: decoded_alu_instruction <= FMIN;
                            4'b1000: decoded_alu_instruction <= FABS;
                            4'b1001: decoded_alu_instruction <= FCVT_W_S;
                            4'b1010: decoded_alu_instruction <= FCVT_S_W;
                            default: $error("Invalid I-type instruction with funct4 %b", funct4);
                        endcase
                    end

                    `OPCODE_M: begin
                        unique case (funct4) 
                            4'b0000: begin
                                // Load instructions (e.g., LW)
                                decoded_rd_address          <= rd;
                                decoded_rs1_address         <= rs1;
                                decoded_reg_write_enable    <= 1;
                                decoded_reg_input_mux       <= LSU_OUT;
                                decoded_immediate           <= sign_extend_15(imm_load);
                                decoded_mem_read_enable     <= 1;
                                decoded_alu_instruction     <= ADDI; // For computing effective address
                            end
                            4'b0001: begin
                                decoded_rs1_address         <= rs1;
                                decoded_rs2_address         <= rs2;
                                decoded_immediate           <= sign_extend_15(imm_s);
                                decoded_mem_write_enable    <= 1;
                                decoded_alu_instruction     <= ADDI; // For computing effective address
                            end
                            default: $error("Invalid M-type instruction with funct4 %b", funct4);
                        endcase
                    end
                    `OPCODE_UP: begin
                        // LUI instruction
                        decoded_rd_address          <= rd;
                        decoded_immediate           <= {imm_u, 12'b0}; // Immediate value shifted left 12 bits
                        decoded_reg_write_enable    <= 1;
                        decoded_reg_input_mux       <= IMMEDIATE;
                    end
                    default: begin
                        // No operation or unrecognized opcode
                    end
                endcase
            end
        end
    end
endmodule

tb/decoder.vcd
$version Generated by VerilatedVcd $end
$date Fri Jun  6 20:55:35 2025 $end
$timescale 1ns $end

 $scope module TOP $end
  $var wire  1 & clk $end
  $var wire  4 4 decoded_alu_instruction [3:0] $end
  $var wire  1 - decoded_branch $end
  $var wire  1 5 decoded_halt $end
  $var wire 32 0 decoded_immediate [31:0] $end
  $var wire  1 , decoded_mem_read_enable $end
  $var wire  1 + decoded_mem_write_enable $end
  $var wire  5 1 decoded_rd_address [4:0] $end
  $var wire  3 . decoded_reg_input_mux [2:0] $end
  $var wire  1 * decoded_reg_write_enable $end
  $var wire  5 2 decoded_rs1_address [4:0] $end
  $var wire  5 3 decoded_rs2_address [4:0] $end
  $var wire  1 / decoded_scalar_instruction $end
  $var wire 32 ) instruction [31:0] $end
  $var wire  1 ' reset $end
  $var wire  3 ( warp_state [2:0] $end
  $scope module decoder $end
   $var wire  1 & clk $end
   $var wire  4 4 decoded_alu_instruction [3:0] $end
   $var wire  1 - decoded_branch $end
   $var wire  1 5 decoded_halt $end
   $var wire 32 0 decoded_immediate [31:0] $end
   $var wire  1 , decoded_mem_read_enable $end
   $var wire  1 + decoded_mem_write_enable $end
   $var wire  5 1 decoded_rd_address [4:0] $end
   $var wire  3 . decoded_reg_input_mux [2:0] $end
   $var wire  1 * decoded_reg_write_enable $end
   $var wire  5 2 decoded_rs1_address [4:0] $end
   $var wire  5 3 decoded_rs2_address [4:0] $end
   $var wire  1 / decoded_scalar_instruction $end
   $var wire  3 : funct3 [2:0] $end
   $var wire  4 < funct4 [3:0] $end
   $var wire 18 $ imm_b [17:0] $end
   $var wire 14 > imm_i [13:0] $end
   $var wire 28 % imm_j [27:0] $end
   $var wire 15 ? imm_load [14:0] $end
   $var wire 15 # imm_s [14:0] $end
   $var wire 20 @ imm_u [31:12] $end
   $var wire  6 7 inst [5:0] $end
   $var wire 32 ) instruction [31:0] $end
   $var wire  3 8 opcode [2:0] $end
   $var wire  5 9 rd [4:0] $end
   $var wire  1 ' reset $end
   $var wire  5 ; rs1 [4:0] $end
   $var wire  5 = rs2 [4:0] $end
   $var wire  1 6 scalar $end
   $var wire  3 ( warp_state [2:0] $end
  $upscope $end
 $upscope $end
$enddefinitions $end


#0
b000000000000000 #
b000000000000000000 $
b0000000000000000000000000000 %
0&
1'
b000 (
b00000000000000000000000000000000 )
0*
0+
0,
0-
b000 .
0/
b00000000000000000000000000000000 0
b00000 1
b00000 2
b00000 3
b0000 4
05
06
b000000 7
b000 8
b00000 9
b000 :
b00000 ;
b0000 <
b00000 =
b00000000000000 >
b000000000000000 ?
b00000000000000000000 @
#1
1&
b1010 4
#2
0&
0'
#3
1&
#4
b000000000000001 #
b000000000000000100 $
b0000000000000110000100000100 %
0&
b010 (
b00000000000000001100000001000001 )
16
b000001 7
b00001 9
b100 :
b00010 ;
b00011 =
b00000000000011 >
b000000000000011 ?
b00000000000001100000 @
#5
1&
1*
1/
b00001 1
b00010 2
b00011 3
b0000 4
#6
0&
b00000000000000001100010001000001 )
b0001 <
b00000000000001100010 @
#7
1&
b0001 4
#8
0&
b00000000000000001100100001000001 )
b0010 <
b00000000000001100100 @
#9
1&
b0010 4
#10
0&
b00000000000000001100110001000001 )
b0011 <
b00000000000001100110 @
#11
1&
b0011 4
#12
0&
b00000000000000001101000001000001 )
b101 :
b0100 <
b00000000000001101000 @
#13
1&
b0100 4
#14
0&
b00000000000000001101010001000001 )
b0101 <
b00000000000001101010 @
